snakelings/__init__.py
snakelings/exercise.py
snakelings/snakelings.py
snakelings-0.1.0.dist-info/entry_points.txt
snakelings-0.1.0.dist-info/WHEEL
snakelings-0.1.0.dist-info/METADATA
snakelings-0.1.0.dist-info/RECORD
