Metadata-Version: 2.1
Name: snakelings
Version: 0.1.0
Summary: 
Author: Chris Blades
Author-email: chrisdblades@gmail.com
Requires-Python: >=3.10,<4.0
Classifier: Programming Language :: Python :: 3
Classifier: Programming Language :: Python :: 3.10
Requires-Dist: appdirs (>=1.4.4,<2.0.0)
Requires-Dist: click (>=8.1.3,<9.0.0)
Requires-Dist: click-default-group (>=1.2.2,<2.0.0)
Requires-Dist: pydantic (>=1.10.1,<2.0.0)
Requires-Dist: pytest (>=7.1.3,<8.0.0)
Requires-Dist: requests (>=2.28.1,<3.0.0)
Requires-Dist: rich (>=12.5.1,<13.0.0)
Requires-Dist: watchdog (>=2.1.9,<3.0.0)
